richerator/__init__.py
richerator/richerator.py
richerator-0.0.6.dist-info/licenses/LICENSE
richerator-0.0.6.dist-info/METADATA
richerator-0.0.6.dist-info/WHEEL
richerator-0.0.6.dist-info/top_level.txt
richerator-0.0.6.dist-info/RECORD
