Metadata-Version: 2.4
Name: richerator
Version: 0.0.6
License-File: LICENSE
Requires-Dist: rich
Dynamic: description
Dynamic: license-file
Dynamic: requires-dist
